easterobot/__init__.py
easterobot/__main__.py
easterobot/bot.py
easterobot/cli.py
easterobot/config.py
easterobot/info.py
easterobot/locker.py
easterobot/logger.py
easterobot/models.py
easterobot/py.typed
easterobot/query.py
easterobot/utils.py
easterobot/alembic/env.py
easterobot/alembic/script.py.mako
easterobot/alembic/versions/2f0d4305e320_init_database.py
easterobot/alembic/versions/940c3b9c702d_add_lock_on_eggs.py
easterobot/casino/__init__.py
easterobot/casino/roulette.py
easterobot/commands/__init__.py
easterobot/commands/base.py
easterobot/commands/basket.py
easterobot/commands/disable.py
easterobot/commands/edit.py
easterobot/commands/enable.py
easterobot/commands/game.py
easterobot/commands/help.py
easterobot/commands/info.py
easterobot/commands/reset.py
easterobot/commands/roulette.py
easterobot/commands/search.py
easterobot/commands/top.py
easterobot/games/__init__.py
easterobot/games/connect4.py
easterobot/games/game.py
easterobot/games/rock_paper_scissor.py
easterobot/games/skyjo.py
easterobot/games/tic_tac_toe.py
easterobot/hunts/__init__.py
easterobot/hunts/hunt.py
easterobot/hunts/luck.py
easterobot/hunts/rank.py
easterobot/resources/alembic.ini
easterobot/resources/config.example.yml
easterobot/resources/credits.txt
easterobot/resources/logging.conf
easterobot/resources/logo.png
easterobot/resources/emotes/eggs/egg_01.png
easterobot/resources/emotes/eggs/egg_02.png
easterobot/resources/emotes/eggs/egg_03.png
easterobot/resources/emotes/eggs/egg_04.png
easterobot/resources/emotes/eggs/egg_05.png
easterobot/resources/emotes/eggs/egg_06.png
easterobot/resources/emotes/eggs/egg_07.png
easterobot/resources/emotes/eggs/egg_08.png
easterobot/resources/emotes/eggs/egg_09.png
easterobot/resources/emotes/eggs/egg_10.png
easterobot/resources/emotes/eggs/egg_11.png
easterobot/resources/emotes/eggs/egg_12.png
easterobot/resources/emotes/eggs/egg_13.png
easterobot/resources/emotes/eggs/egg_14.png
easterobot/resources/emotes/eggs/egg_15.png
easterobot-1.5.2.dist-info/METADATA
easterobot-1.5.2.dist-info/WHEEL
easterobot-1.5.2.dist-info/entry_points.txt
easterobot-1.5.2.dist-info/licenses/LICENSE
easterobot-1.5.2.dist-info/RECORD
