Metadata-Version: 2.4
Name: easterobot
Version: 1.5.2
Summary: Discord bot for Easter.
Project-URL: Homepage, https://github.com/Dashstrom/easterobot
Project-URL: Repository, https://github.com/Dashstrom/easterobot
Project-URL: Documentation, https://dashstrom.github.io/easterobot
Author-email: Dashstrom <dashstrom.pro@gmail.com>
License-File: LICENSE
Keywords: bot,discord,easter,eggs,hunt
Classifier: Development Status :: 4 - Beta
Classifier: Environment :: Console
Classifier: Framework :: Pytest
Classifier: Framework :: Sphinx
Classifier: Intended Audience :: Developers
Classifier: Intended Audience :: System Administrators
Classifier: License :: OSI Approved :: MIT License
Classifier: Natural Language :: English
Classifier: Operating System :: OS Independent
Classifier: Programming Language :: Python :: 3
Classifier: Programming Language :: Python :: 3 :: Only
Classifier: Programming Language :: Python :: 3.9
Classifier: Programming Language :: Python :: 3.10
Classifier: Programming Language :: Python :: 3.11
Classifier: Programming Language :: Python :: 3.12
Classifier: Programming Language :: Python :: 3.13
Classifier: Typing :: Typed
Requires-Python: <4.0,>=3.9
Requires-Dist: aiosqlite>=0.21.0
Requires-Dist: alembic>=1.15.2
Requires-Dist: asyncpg>=0.30.0
Requires-Dist: discord-py>=2.5.2
Requires-Dist: msgspec>=0.19.0
Requires-Dist: pyyaml>=6.0.2
Requires-Dist: sqlalchemy[asyncio]>=2.0.40
Requires-Dist: typing-extensions>=4.8.0
